{
  "publicPath": "/_nuxt/",
  "all": [
    "../server/index.spa.html",
    "../server/index.ssr.html",
    "1469afcdd0a2536ec8fe.js",
    "1788bb34f3192ed93fde.js",
    "4a8cc98dc03b8f7052b7.js",
    "8e2634a1a3712d045345.js",
    "92eacc435d6df935195b.js",
    "932c88a371cea0036bf9.js",
    "LICENSES",
    "b3c275d06e14d9fdc2d8.js",
    "cacc4870a3ffc5461d6a.js",
    "d1db6a05c0306611503b.js",
    "efb5b21dc21bfd141332.js",
    "fonts/535877f.woff",
    "fonts/732389d.ttf"
  ],
  "initial": [
    "efb5b21dc21bfd141332.js",
    "1788bb34f3192ed93fde.js",
    "d1db6a05c0306611503b.js",
    "4a8cc98dc03b8f7052b7.js"
  ],
  "async": [
    "1469afcdd0a2536ec8fe.js",
    "8e2634a1a3712d045345.js",
    "92eacc435d6df935195b.js",
    "932c88a371cea0036bf9.js",
    "b3c275d06e14d9fdc2d8.js",
    "cacc4870a3ffc5461d6a.js"
  ],
  "modules": {
    "10455750": [
      11,
      13,
      14
    ],
    "13039385": [
      11,
      13,
      14
    ],
    "16499632": [
      4
    ],
    "26728156": [
      11,
      13,
      14
    ],
    "31058161": [
      3
    ],
    "38537926": [
      3
    ],
    "46394522": [
      3
    ],
    "47931472": [
      5
    ],
    "49375127": [
      5
    ],
    "51381241": [
      4
    ],
    "54803678": [
      4
    ],
    "60435444": [
      3
    ],
    "73793180": [
      11,
      13,
      14
    ],
    "75910742": [
      11,
      13,
      14
    ],
    "79389814": [
      11,
      13,
      14
    ],
    "81408172": [
      11,
      13,
      14
    ],
    "84736414": [
      11,
      13,
      14
    ],
    "85590488": [
      3
    ],
    "7c6f4f40": [
      3
    ],
    "19b74ca8": [
      4
    ],
    "7779ee4e": [
      11,
      13,
      14
    ],
    "1a8d90a0": [
      11,
      13,
      14
    ],
    "44a36c75": [
      11,
      13,
      14
    ],
    "10fa3988": [
      3
    ],
    "60ab5de7": [
      3
    ],
    "3bbaa5d5": [
      11,
      13,
      14
    ],
    "2e608ca5": [
      3
    ],
    "4d728432": [
      3
    ],
    "5a4a4c07": [
      11,
      13,
      14
    ],
    "79fe2c39": [
      3
    ],
    "306e36f4": [
      3
    ],
    "aa2b03fc": [
      3
    ],
    "244f6a52": [
      11,
      13,
      14
    ],
    "631531e8": [
      3
    ],
    "016932b8": [
      3
    ],
    "4294dd1e": [
      3
    ],
    "a050db0c": [
      3
    ],
    "ccb0d7f4": [
      3
    ],
    "ccbdb12e": [
      3
    ],
    "d1c41a34": [
      3
    ],
    "0fa19334": [
      3
    ],
    "7accd362": [
      3
    ],
    "4685c18c": [
      3
    ],
    "b668215c": [
      3
    ],
    "754ef052": [
      11,
      13,
      14
    ],
    "7e34c4e1": [
      3
    ],
    "4f98576b": [
      3
    ],
    "65b38625": [
      4
    ],
    "1eddf7b2": [
      11,
      13,
      14
    ],
    "3e6d3568": [
      4
    ],
    "5bad11a1": [
      4
    ],
    "e48cccd6": [
      4
    ],
    "0e1f2060": [
      4
    ],
    "74091c50": [
      4
    ],
    "38232d34": [
      4
    ],
    "9e29ae96": [
      4
    ],
    "f65e6d14": [
      4
    ],
    "44e68216": [
      4
    ],
    "c72251c8": [
      4
    ],
    "03fad2e8": [
      4
    ],
    "7c108589": [
      4
    ],
    "aa940fc2": [
      4
    ],
    "22cdeed0": [
      4
    ],
    "53b26802": [
      4
    ],
    "cab4e760": [
      4
    ],
    "471704ad": [
      4
    ],
    "09ef6618": [
      4
    ],
    "06f43df5": [
      4
    ],
    "55f7416c": [
      4
    ],
    "674f2107": [
      4
    ],
    "9c2fba9e": [
      4
    ],
    "031637dd": [
      4
    ],
    "5fa0cff9": [
      4
    ],
    "5e128f89": [
      4
    ],
    "034cd98a": [
      4
    ],
    "74436e92": [
      4
    ],
    "6e0c37de": [
      4
    ],
    "531da9ae": [
      3
    ],
    "d78a8786": [
      3
    ],
    "6a622864": [
      3
    ],
    "3ebce6ac": [
      3
    ],
    "9f43ce32": [
      3
    ],
    "5711d9ab": [
      3
    ],
    "2fbdd093": [
      3
    ],
    "69bdf3c6": [
      3
    ],
    "494b725c": [
      11,
      13,
      14
    ],
    "17f5eb28": [
      11,
      13,
      14
    ],
    "d1f871bc": [
      3
    ],
    "3f0b8adf": [
      3
    ],
    "005ab6b5": [
      3
    ],
    "5962773c": [
      3
    ],
    "a285bf6a": [
      3
    ],
    "202e5b7d": [
      3
    ],
    "5d1eac16": [
      3
    ],
    "7c0eab41": [
      3
    ],
    "c4c180ee": [
      3
    ],
    "d8279f90": [
      11,
      13,
      14
    ],
    "9a3d652c": [
      3
    ],
    "f0304d7a": [
      3
    ],
    "250ba8e0": [
      3
    ],
    "d28a6e82": [
      11,
      13,
      14
    ],
    "7c0eda4f": [
      11,
      13,
      14
    ],
    "27bf5454": [
      11,
      13,
      14
    ],
    "af5e0a90": [
      11,
      13,
      14
    ],
    "c8dd15f4": [
      3
    ],
    "7f441405": [
      3
    ],
    "609dee1c": [
      3
    ],
    "8e07d6ba": [
      3
    ],
    "7bb7bc64": [
      3
    ],
    "042e1c7e": [
      3
    ],
    "b14a43e6": [
      3
    ],
    "14671bea": [
      3
    ],
    "b14ecf9c": [
      3
    ],
    "6180eb0e": [
      3
    ],
    "7f025992": [
      3
    ],
    "41fdc74b": [
      3
    ],
    "16ace2bf": [
      3
    ],
    "3d0a85ba": [
      11,
      13,
      14
    ],
    "2994fe7c": [
      11,
      13,
      14
    ],
    "45def707": [
      11,
      13,
      14
    ],
    "e1a2b8ca": [
      11,
      13,
      14
    ],
    "61e33086": [
      3
    ],
    "4a02669c": [
      3
    ],
    "3dac6f43": [
      3
    ],
    "1ec3aeaa": [
      3
    ],
    "663141f5": [
      3
    ],
    "c14e05aa": [
      3
    ],
    "4ef82970": [
      4
    ],
    "3add0688": [
      4
    ],
    "3b7d23ea": [
      4
    ],
    "d63b4162": [
      4
    ],
    "0e6b4056": [
      4
    ],
    "34a7669e": [
      4
    ],
    "3da5a7a4": [
      4
    ],
    "1303d048": [
      4
    ],
    "2cb0b670": [
      4
    ],
    "62cc4f5a": [
      11,
      13,
      14
    ],
    "7ccf31c4": [
      4
    ],
    "6aabf4fc": [
      3
    ],
    "14e31a33": [
      3
    ],
    "6be7cb5e": [
      3
    ],
    "f7c0e7e6": [
      3
    ],
    "5c677452": [
      3
    ],
    "b157e708": [
      3
    ],
    "1ca14647": [
      3
    ],
    "5f49c871": [
      3
    ],
    "562fa49a": [
      3
    ],
    "7dc723ea": [
      3
    ],
    "83eb13e8": [
      3
    ],
    "dc78e246": [
      3
    ],
    "a1bfbf9e": [
      11,
      13,
      14
    ],
    "28accee1": [
      11,
      13,
      14
    ],
    "0b863e96": [
      3
    ],
    "aa3ca198": [
      3
    ],
    "04414a9c": [
      3
    ],
    "37574f06": [
      3
    ],
    "54fdfb92": [
      3
    ],
    "fa6a8338": [
      3
    ],
    "a418d1a8": [
      3
    ],
    "7aa524ec": [
      3
    ],
    "ee11ad58": [
      3
    ],
    "04ab1de0": [
      3
    ],
    "8b175540": [
      3
    ],
    "718014f2": [
      3
    ],
    "5e541420": [
      3
    ],
    "fac78c10": [
      11,
      13,
      14
    ],
    "91ccf93a": [
      4
    ],
    "4da3058c": [
      11,
      13,
      14
    ],
    "5939e954": [
      3
    ],
    "00084452": [
      3
    ],
    "ab716e04": [
      3
    ],
    "7030d85f": [
      3
    ],
    "1f814957": [
      3
    ],
    "38ba9b56": [
      3
    ],
    "ca50bb5e": [
      3
    ],
    "7c2e77c8": [
      3
    ],
    "22d2ac00": [
      3
    ],
    "621a6409": [
      3
    ],
    "ab357846": [
      3
    ],
    "593b9a42": [
      3
    ],
    "01798693": [
      3
    ],
    "ea665556": [
      3
    ],
    "0914f1dc": [
      3
    ],
    "14bf56de": [
      3
    ],
    "05180fc3": [
      3
    ],
    "6830d11e": [
      3
    ],
    "2d93e328": [
      3
    ],
    "f8cad216": [
      3
    ],
    "734b4093": [
      3
    ],
    "12a482e8": [
      3
    ],
    "34e2065c": [
      3
    ],
    "0221e626": [
      11,
      13,
      14
    ],
    "7900ba50": [
      3
    ],
    "0aac94ec": [
      3
    ],
    "0f982cb8": [
      3
    ],
    "42e9d61c": [
      3
    ],
    "5ded99cc": [
      3
    ],
    "42f86b75": [
      3
    ],
    "09062cf2": [
      3
    ],
    "2241afce": [
      3
    ],
    "3c07f196": [
      11,
      13,
      14
    ],
    "220846cd": [
      11,
      13,
      14
    ],
    "14f9cdd8": [
      11,
      13,
      14
    ],
    "5a800eea": [
      11,
      13,
      14
    ],
    "da39b650": [
      11,
      13,
      14
    ],
    "3e4a4e3e": [
      11,
      13,
      14
    ],
    "a23c46be": [
      11,
      13,
      14
    ],
    "a8f609dc": [
      3
    ],
    "88113abc": [
      3
    ],
    "43b0b001": [
      3
    ],
    "1a4dd75d": [
      3
    ],
    "47cf7c8b": [
      3
    ],
    "0c04e235": [
      3
    ],
    "40a2cffb": [
      3
    ],
    "2886618a": [
      3
    ],
    "7aa2df11": [
      3
    ],
    "415b9178": [
      11,
      13,
      14
    ],
    "af618244": [
      3
    ],
    "6244683b": [
      11,
      13,
      14
    ],
    "7d89cb62": [
      11,
      13,
      14
    ],
    "489689fe": [
      3
    ],
    "03d0b720": [
      11,
      13,
      14
    ],
    "55d2afc8": [
      11,
      13,
      14
    ],
    "ea3d3862": [
      11,
      13,
      14
    ],
    "08a1f664": [
      11,
      13,
      14
    ],
    "411af800": [
      11,
      13,
      14
    ],
    "ab318074": [
      11,
      13,
      14
    ],
    "f37ee6a8": [
      11,
      13,
      14
    ],
    "59d5f818": [
      11,
      13,
      14
    ],
    "669a9853": [
      11,
      13,
      14
    ],
    "3bfceb76": [
      11,
      13,
      14
    ],
    "6a2342a6": [
      11,
      13,
      14
    ],
    "fd93813e": [
      11,
      13,
      14
    ],
    "22600b25": [
      11,
      13,
      14
    ],
    "7476719a": [
      11,
      13,
      14
    ],
    "3fd6eb0a": [
      11,
      13,
      14
    ],
    "76b74166": [
      11,
      13,
      14
    ],
    "5e46f7b1": [
      11,
      13,
      14
    ],
    "3d14091d": [
      4
    ],
    "41dd919c": [
      3
    ],
    "485d5af4": [
      4
    ],
    "653fa18a": [
      4
    ],
    "78e872fa": [
      3
    ],
    "aea5ff16": [
      3
    ],
    "0055f62f": [
      3
    ],
    "29bc3a50": [
      3
    ],
    "0572ae90": [
      3
    ],
    "ccad417a": [
      3
    ],
    "38a9c7e6": [
      3
    ],
    "5f1aa35e": [
      3
    ],
    "7b35fc01": [
      3
    ],
    "72aec3f7": [
      3
    ],
    "353aff25": [
      3
    ],
    "1919e9d4": [
      3
    ],
    "3771ea12": [
      3
    ],
    "741b9d11": [
      3
    ],
    "16c40bed": [
      3
    ],
    "7267eb5a": [
      3
    ],
    "7e1cbab7": [
      3
    ],
    "09bef92d": [
      3
    ],
    "a09fc0a0": [
      3
    ],
    "3a347f86": [
      3
    ],
    "49f793e5": [
      3
    ],
    "c9d7b576": [
      3
    ],
    "8ff9cbb4": [
      3
    ],
    "15ea456e": [
      3
    ],
    "7e3fa562": [
      3
    ],
    "1a68096e": [
      3
    ],
    "2e0b9088": [
      3
    ],
    "320b192d": [
      3
    ],
    "666252a0": [
      3
    ],
    "26515c9c": [
      3
    ],
    "aa10e116": [
      3
    ],
    "ffd3f43a": [
      3
    ],
    "6c78d002": [
      3
    ],
    "cb497444": [
      3
    ],
    "797be66c": [
      3
    ],
    "4b5b12c9": [
      3
    ],
    "15f3e549": [
      3
    ],
    "30fe2340": [
      3
    ],
    "71474dc4": [
      3
    ],
    "97f43282": [
      3
    ],
    "7ea5ddd1": [
      3
    ],
    "26ca97f6": [
      4
    ],
    "35039e91": [
      4
    ],
    "0f8261c2": [
      4
    ],
    "73942d9d": [
      4
    ],
    "750d4f44": [
      11,
      13,
      14
    ],
    "09671583": [
      11,
      13,
      14
    ],
    "5e039738": [
      4
    ],
    "05182123": [
      4
    ],
    "7b793599": [
      4
    ],
    "2ee118ae": [
      4
    ],
    "062723fe": [
      4
    ],
    "9fbd5768": [
      4
    ],
    "08893a41": [
      4
    ],
    "29b366c6": [
      4
    ],
    "c307bdfe": [
      11,
      13,
      14
    ],
    "3f58eb52": [
      11,
      13,
      14
    ],
    "f0b67638": [
      11,
      13,
      14
    ],
    "8dae6f50": [
      11,
      13,
      14
    ],
    "7365e43c": [
      11,
      13,
      14
    ],
    "24d21c48": [
      11,
      13,
      14
    ],
    "a47b2c28": [
      11,
      13,
      14
    ],
    "3d4bcd47": [
      11,
      13,
      14
    ],
    "64af274c": [
      11,
      13,
      14
    ],
    "3a760d46": [
      11,
      13,
      14
    ],
    "2c57ecb9": [
      11,
      13,
      14
    ],
    "c93c75f8": [
      11,
      13,
      14
    ],
    "627a2598": [
      11,
      13,
      14
    ],
    "75ae1906": [
      11,
      13,
      14
    ],
    "64cfc83e": [
      11,
      13,
      14
    ],
    "0b341be6": [
      11,
      13,
      14
    ],
    "6fc34d0c": [
      11,
      13,
      14
    ],
    "4e27a035": [
      11,
      13,
      14
    ],
    "9abaee74": [
      11,
      13,
      14
    ],
    "65a2a912": [
      11,
      13,
      14
    ],
    "3507da0f": [
      11,
      13,
      14
    ],
    "cddbe4e8": [
      11,
      13,
      14
    ],
    "6038635f": [
      11,
      13,
      14
    ],
    "1b405f11": [
      11,
      13,
      14
    ],
    "365e333c": [
      11,
      13,
      14
    ],
    "8399abc6": [
      11,
      13,
      14
    ],
    "40d263fd": [
      4
    ],
    "e708c6f2": [
      4
    ],
    "9111f05c": [
      4
    ],
    "6f4eb960": [
      4
    ],
    "1957e2ca": [
      4
    ],
    "0b91483c": [
      4
    ],
    "f6e68bde": [
      4
    ],
    "20e233ea": [
      4
    ],
    "cc44b482": [
      4
    ],
    "3029de54": [
      3
    ],
    "1986a594": [
      3
    ],
    "6b0364cb": [
      3
    ],
    "61ff5736": [
      3
    ],
    "a4e028e8": [
      3
    ],
    "d727dc2a": [
      3
    ],
    "f99a61bc": [
      3
    ],
    "0e0c0cda": [
      3
    ],
    "8f6dc90c": [
      3
    ],
    "4042a3f0": [
      3
    ],
    "2fab28dc": [
      3
    ],
    "0ddebd53": [
      3
    ],
    "ebfde3f2": [
      3
    ],
    "78f0784c": [
      3
    ],
    "43f44af2": [
      11,
      13,
      14
    ],
    "43e86d9f": [
      11,
      13,
      14
    ],
    "4ed01c22": [
      4
    ],
    "157a3626": [
      4
    ],
    "328000cd": [
      11,
      13,
      14
    ],
    "31b3a5a4": [
      11,
      13,
      14
    ],
    "5c7485d8": [
      11,
      13,
      14
    ],
    "846afe44": [
      11,
      13,
      14
    ],
    "3460f70a": [
      11,
      13,
      14
    ],
    "e186b9f0": [
      11,
      13,
      14
    ],
    "49d54a34": [
      11,
      13,
      14
    ],
    "ceb20af2": [
      11,
      13,
      14
    ],
    "59555d38": [
      11,
      13,
      14
    ],
    "99169dba": [
      11,
      13,
      14
    ],
    "5bd56a9a": [
      11,
      13,
      14
    ],
    "2c7dc87c": [
      11,
      13,
      14
    ],
    "8780d372": [
      11,
      13,
      14
    ],
    "3fe7a330": [
      11,
      13,
      14
    ],
    "4583e368": [
      11,
      13,
      14
    ],
    "009adb88": [
      11,
      13,
      14
    ],
    "77e359a1": [
      11,
      13,
      14
    ],
    "267e58b0": [
      11,
      13,
      14
    ],
    "7e59bd63": [
      11,
      13,
      14
    ],
    "1464d4a2": [
      11,
      13,
      14
    ],
    "df4106c6": [
      11,
      13,
      14
    ],
    "5ffc7fc8": [
      11,
      13,
      14
    ],
    "287506a9": [
      11,
      13,
      14
    ],
    "53ccd74a": [
      11,
      13,
      14
    ],
    "762f7861": [
      11,
      13,
      14
    ],
    "bcf16dfc": [
      11,
      13,
      14
    ],
    "7bba8f4b": [
      11,
      13,
      14
    ],
    "70715eef": [
      11,
      13,
      14
    ],
    "1086fbb1": [
      11,
      13,
      14
    ],
    "137ac340": [
      11,
      13,
      14
    ],
    "39e734d6": [
      11,
      13,
      14
    ],
    "2cf8ff60": [
      11,
      13,
      14
    ],
    "6b9e8441": [
      11,
      13,
      14
    ],
    "535c6fe2": [
      11,
      13,
      14
    ],
    "7eb44083": [
      11,
      13,
      14
    ],
    "2cf6db04": [
      11,
      13,
      14
    ],
    "7f8fa9bd": [
      11,
      13,
      14
    ],
    "119d3adf": [
      11,
      13,
      14
    ],
    "765ac77d": [
      11,
      13,
      14
    ],
    "0c65debc": [
      11,
      13,
      14
    ],
    "738e6454": [
      11,
      13,
      14
    ],
    "283490b5": [
      11,
      13,
      14
    ],
    "3b9d27f1": [
      11,
      13,
      14
    ],
    "87687c62": [
      11,
      13,
      14
    ],
    "34e22082": [
      11,
      13,
      14
    ],
    "58aeb8a3": [
      11,
      13,
      14
    ],
    "62f146cd": [
      11,
      13,
      14
    ],
    "752c0963": [
      3
    ],
    "5b9a59d0": [
      3
    ],
    "481e20be": [
      3
    ],
    "06a99da5": [
      3
    ],
    "1ca00668": [
      3
    ],
    "72c7bcca": [
      3
    ],
    "488bc766": [
      3
    ],
    "b0a57312": [
      3
    ],
    "6dbfba87": [
      11,
      13,
      14
    ],
    "4757a0c6": [
      3
    ],
    "c0e9d47a": [
      3
    ],
    "afc48814": [
      3
    ],
    "7bf74754": [
      3
    ],
    "e9705120": [
      3
    ],
    "78b52c44": [
      3
    ],
    "df36e05e": [
      3
    ],
    "70d154a4": [
      3
    ],
    "5d6a8b06": [
      3
    ],
    "4511e8a0": [
      3
    ],
    "84511c78": [
      3
    ],
    "25040b1d": [
      11,
      13,
      14
    ],
    "c49a48de": [
      3
    ],
    "263bb228": [
      3
    ],
    "9a2cf578": [
      3
    ],
    "7d738af6": [
      3
    ],
    "6fdc74b3": [
      3
    ],
    "641862bd": [
      3
    ],
    "7a9e535b": [
      3
    ],
    "a9d18968": [
      3
    ],
    "e7d33d50": [
      3
    ],
    "ff048398": [
      3
    ],
    "82db0b70": [
      11,
      13,
      14
    ],
    "549d9187": [
      11,
      13,
      14
    ],
    "052edd16": [
      11,
      13,
      14
    ],
    "2605109d": [
      3
    ],
    "57cf5682": [
      11,
      13,
      14
    ],
    "0c469c78": [
      11,
      13,
      14
    ],
    "4fb028e8": [
      11,
      13,
      14
    ],
    "44c3f56e": [
      11,
      13,
      14
    ],
    "51bfa57f": [
      11,
      13,
      14
    ],
    "2a17c2af": [
      11,
      13,
      14
    ],
    "1f7992b6": [
      11,
      13,
      14
    ],
    "5b22a987": [
      11,
      13,
      14
    ],
    "5c154440": [
      11,
      13,
      14
    ],
    "49430dc2": [
      11,
      13,
      14
    ],
    "f7393eb6": [
      11,
      13,
      14
    ],
    "043e6b91": [
      11,
      13,
      14
    ],
    "d129f662": [
      11,
      13,
      14
    ],
    "0f46fa4e": [
      11,
      13,
      14
    ],
    "4c440f02": [
      11,
      13,
      14
    ],
    "52cd1cf1": [
      11,
      13,
      14
    ],
    "ee0e8770": [
      11,
      13,
      14
    ],
    "e2407a96": [
      11,
      13,
      14
    ],
    "56a7f052": [
      11,
      13,
      14
    ],
    "6dd0488c": [
      11,
      13,
      14
    ],
    "dd536006": [
      11,
      13,
      14
    ],
    "c5c1a6da": [
      11,
      13,
      14
    ],
    "61b2e7ec": [
      11,
      13,
      14
    ],
    "2230e552": [
      4
    ],
    "f18230c2": [
      4
    ],
    "241d1e0a": [
      4
    ],
    "0b9de5d3": [
      4
    ],
    "8fba0e2a": [
      4
    ],
    "0e25f53c": [
      4
    ],
    "1d101eb2": [
      4
    ],
    "25f58f42": [
      4
    ],
    "bd21c634": [
      4
    ],
    "fde9d980": [
      4
    ],
    "589535c0": [
      4
    ],
    "e2b5aa34": [
      4
    ],
    "67bf8dc1": [
      4
    ],
    "5488d71a": [
      4
    ],
    "08752ebc": [
      4
    ],
    "9ec3ee2c": [
      4
    ],
    "6611a4f4": [
      4
    ],
    "16073bd7": [
      4
    ],
    "9d2045b0": [
      4
    ],
    "6027af38": [
      4
    ],
    "26976a62": [
      4
    ],
    "141560b4": [
      4
    ],
    "2bdbb19a": [
      4
    ],
    "82d57e1c": [
      4
    ],
    "abc263ce": [
      4
    ],
    "68fc3246": [
      4
    ],
    "06ca3cc8": [
      4
    ],
    "758a5a30": [
      4
    ],
    "97f1d11c": [
      6
    ],
    "0797b0ba": [
      2
    ],
    "5d631cae": [
      5
    ],
    "1076d282": [
      7
    ],
    "68384eb8": [
      6
    ],
    "be70caa2": [
      6
    ],
    "e0353756": [
      2
    ],
    "8a3e60c0": [
      2
    ],
    "78622f64": [
      5
    ],
    "7cc10aa8": [
      5
    ],
    "3ab1a991": [
      5
    ],
    "1924514a": [
      5
    ],
    "cc3ebfb4": [
      5
    ],
    "6eec9110": [
      7
    ],
    "42f972b6": [
      7
    ],
    "05e9755a": [
      6
    ],
    "8b1007f8": [
      6
    ],
    "98200ee4": [
      6
    ],
    "b1ae1190": [
      6
    ],
    "107dd0a2": [
      6
    ],
    "08aaffc4": [
      6
    ],
    "2280c341": [
      6
    ],
    "13c61c47": [
      9
    ],
    "1ac7fa43": [
      9
    ],
    "96b411bc": [
      9
    ],
    "712e7d8f": [
      9
    ],
    "32e913a1": [
      9
    ],
    "cab9fe18": [
      9
    ],
    "62904ef4": [
      2
    ],
    "705a8393": [
      2
    ],
    "d13111e6": [
      2
    ],
    "168cfc72": [
      2
    ],
    "2b6d51ee": [
      2
    ],
    "c1c2f2b0": [
      2
    ],
    "eb35e272": [
      5
    ],
    "de4f84da": [
      5
    ],
    "5d46cecc": [
      5
    ],
    "1b7d0bfb": [
      5
    ],
    "ec9f63f4": [
      5
    ],
    "95751ec2": [
      10
    ],
    "02574a78": [
      10
    ],
    "431e4a7c": [
      10
    ],
    "f43f18a8": [
      10
    ],
    "2241f9e3": [
      10
    ],
    "ae3cc254": [
      7
    ],
    "571f775e": [
      7
    ],
    "5133b31a": [
      7
    ],
    "4db151aa": [
      7
    ],
    "1b5c4e32": [
      7
    ]
  },
  "assetsMapping": {
    "1469afcdd0a2536ec8fe.js": "362c7694",
    "1788bb34f3192ed93fde.js": "0859c165",
    "4a8cc98dc03b8f7052b7.js": "1a3ae26b",
    "8e2634a1a3712d045345.js": "2b35ffc9",
    "92eacc435d6df935195b.js": "ba0e8456",
    "932c88a371cea0036bf9.js": "3cdf16e1",
    "b3c275d06e14d9fdc2d8.js": "90080f22",
    "cacc4870a3ffc5461d6a.js": "36446f21",
    "d1db6a05c0306611503b.js": "7ea1d828",
    "efb5b21dc21bfd141332.js": "6fca0322"
  }
}